<?xml version="1.0" encoding="utf-8"?>
<mainadvertise>

    <advertise id="1">
        <title>广告1</title>
        <imageName>main1</imageName>
        <url>http://images.enrz.com/wp-content/uploads/2016/10/285A8322.jpg</url>
    </advertise>
    
    <advertise id="2">
        <title>广告2</title>
        <imageName>main2</imageName>
        <url>http://images.enrz.com/wp-content/uploads/2016/08/50A6614.jpg</url>
    </advertise>
    
    <advertise id="3">
        <title>广告3</title>
        <imageName>main3</imageName>
        <url>http://images.enrz.com/wp-content/uploads/2016/12/fanbingbing.jpg</url>
    </advertise>
    
    <advertise id="4">
        <title>广告4</title>
        <imageName>main4</imageName>
        <url>http://images.enrz.com/wp-content/uploads/2016/12/yangmi.jpg</url>
    </advertise>
    
    <menu id ="1">
        <title>优美高清</title>
        <imageName>g1</imageName>
        <url>http://css.taoguba.com.cn/images/tgb_con.gif</url>
        <subName>UmeiActivity.class</subName>
        <subUrl>com.fgj.urose.umei.UmeiActivity</subUrl>
        <subAction></subAction>
    </menu>
    
    <menu id ="2">
        <title>美衣</title>
        <imageName>g2</imageName>
        <url>http://css.taoguba.com.cn/images/tgb_con.gif</url>
        <subName></subName>
        <subUrl></subUrl>
        <subAction></subAction>
    </menu>
    
    <menu id ="3">
        <title>男友衣柜</title>
        <imageName>g3</imageName>
        <url>http://css.taoguba.com.cn/images/tgb_con.gif</url>
        <subName></subName>
        <subUrl></subUrl>
        <subAction></subAction>
    </menu>
    
    <menu id ="4">
        <title>美肤</title>
        <imageName>g4</imageName>
        <url>http://css.taoguba.com.cn/images/tgb_con.gif</url>
        <subName></subName>
        <subUrl></subUrl>
        <subAction></subAction>
    </menu>
    
    <menu id ="5">
        <title>家具</title>
        <imageName>g5</imageName>
        <url>http://css.taoguba.com.cn/images/tgb_con.gif</url>
        <subName></subName>
        <subUrl></subUrl>
        <subAction></subAction>
    </menu>
    
    <menu id ="6">
        <title>美鞋</title>
        <imageName>g6</imageName>
        <url>http://css.taoguba.com.cn/images/tgb_con.gif</url>
        <subName></subName>
        <subUrl></subUrl>
        <subAction></subAction>
    </menu>
    
    <menu id ="7">
        <title>添加</title>
        <imageName>g7</imageName>
        <url>http://css.taoguba.com.cn/images/tgb_con.gif</url>
        <subName></subName>
        <subUrl></subUrl>
        <subAction></subAction>
    </menu>
    
    

</mainadvertise>